fast_mcp/__init__.py
fast_mcp/chat.py
fast_mcp/core.py
fast_mcp/utils.py
fast_mcp/ai/__init__.py
fast_mcp/ai/inference.py
fast_mcp/ai/provider.py
fast_mcp/ai/tokenizer.py
fast_mcp/constants/__init__.py
fast_mcp/constants/classifiers.py
fast_mcp/structures/__init__.py
fast_mcp/structures/context.py
fast_mcp/structures/llm_config.py
fast_mcp/structures/message.py
fast_mcp/structures/taggers.py
leonbonetti_fast_mcp-0.1.1.dist-info/METADATA
leonbonetti_fast_mcp-0.1.1.dist-info/WHEEL
leonbonetti_fast_mcp-0.1.1.dist-info/top_level.txt
leonbonetti_fast_mcp-0.1.1.dist-info/RECORD
