Metadata-Version: 2.4
Name: leonbonetti.fast-mcp
Version: 0.1.1
Summary: Small selection of utilities for python ai processes
Home-page: https://github.com/LeonBonetti/FastMCP
Author: Leonardo Bonetti
Author-email: leonardobonetti.w@gmail.com
License: proprietary
Classifier: Topic :: Utilities
Classifier: License :: Other/Proprietary License
Requires-Dist: langchain==0.3.21
Requires-Dist: langchain-core==0.3.47
Requires-Dist: langchain-openai==0.3.9
Requires-Dist: langchain-text-splitters==0.3.7
Requires-Dist: langsmith==0.3.18
Requires-Dist: tiktoken==0.9.0
Dynamic: author
Dynamic: author-email
Dynamic: classifier
Dynamic: description
Dynamic: description-content-type
Dynamic: home-page
Dynamic: license
Dynamic: requires-dist
Dynamic: summary
